{"title": "Luxury Travel Co | Premium Luxury Travel Packages", "meta_description": "Experience the ultimate in luxury with our curated travel packages. Exclusive destinations, personalized itineraries, and 5-star service for discerning travelers.", "meta_keywords": "luxury travel packages, bespoke vacations, exclusive travel experiences, high-end itineraries", "h1": "Crafted Luxury Travel Packages", "h2": ["Tailored for the Discerning Traveler", "World-Class Destinations", "White-Glove Service"]}"